[
  {
    "id": "06941826-f018-4e61-a7ad-60cabfa25eb1",
    "title": "Selling gpu",
    "body": "The gpu is in the best condition",
    "author": "Pavel Kocev",
    "date": "16.03.2023",
    "tags": [
      "games",
      "gamess"
    ]
  },
  {
    "id": "69c0ed9b-d2e0-46a2-93d6-273fe293d905",
    "title": "Selling gpu",
    "body": "The gpu is in the best condition",
    "author": "Pavel Kocev",
    "date": "16.03.2023",
    "tags": [
      "eldenRing",
      "life"
    ]
  },
  {
    "id": "2e87fe78-b371-4c95-b246-e55dc4fb1fda",
    "title": "Selling gpu",
    "body": "The gpu is in the best condition",
    "author": "Pavel Kocev",
    "date": "16.03.2023",
    "tags": [
      "fortnite",
      "play"
    ]
  },
  {
    "id": "7bfa5b97-edf9-442c-ae83-19cc425207ba",
    "title": "Selling gpu",
    "body": "The gpu is in the best condition",
    "author": "Pavel Kocev",
    "date": "16.03.2023",
    "tags": [
      "games",
      "gamess"
    ]
  },
  {
    "id": "2d4f6407-7803-459a-8b85-0cfe5f7eceda",
    "title": "ADED gpu",
    "body": "The gpu is in the best condition",
    "author": "Pavel Kocev",
    "date": "16.03.2023",
    "tags": [
      "games",
      "gamess"
    ]
  },
  {
    "id": "3660acdb-c404-4b55-aec8-646bce8369cd",
    "title": "ADED gpu",
    "body": "The gpu is in the best condition",
    "author": "Pavel Kocev",
    "date": "16.03.2023",
    "tags": [
      "games",
      "gamess"
    ]
  },
  {
    "id": "be4b7a28-3ad7-4de3-bf10-3e3c636eac42",
    "title": "Selling gpu",
    "body": "The gpu is in the best condition",
    "author": "Pavel Kocev",
    "date": "16.03.2023",
    "tags": [
      "fortnite",
      "play"
    ]
  },
  {
    "id": "5d533998-b594-4398-8deb-b0d03c6f9320",
    "title": "Selling gpu",
    "body": "The gpu is in the best condition",
    "author": "Pavel Kocev",
    "date": "16.03.2023",
    "tags": [
      "games",
      "gamess"
    ]
  },
  {
    "id": "8116cd14-bc79-41ea-b4eb-c62b591041a7",
    "title": "Selling gpu",
    "body": "The gpu is in the best condition",
    "author": "Pavel Kocev",
    "date": "16.03.2023",
    "tags": [
      "games",
      "gamess"
    ]
  },
  {
    "id": "adda2132-82ed-4c2f-a88f-ef564fc09bdc",
    "title": "Selling gpu",
    "body": "The gpu is in the best condition",
    "author": "Pavel Kocev",
    "date": "16.03.2023",
    "tags": [
      "games",
      "gamess"
    ]
  },
  {
    "id": "73c427c8-8f50-401a-b5c9-c3c2dcb390c0",
    "title": "Selling gpu",
    "body": "The gpu is in the best condition",
    "author": "Pavel Kocev",
    "date": "16.03.2023",
    "tags": [
      "games",
      "gamess"
    ]
  },
  {
    "id": "72b4ef97-114b-42ef-ac8f-f86aa6ae6259",
    "title": "Selling gpu",
    "body": "The gpu is in the best condition",
    "author": "Pavel Kocev",
    "date": "16.03.2023",
    "tags": [
      "games",
      "gamess"
    ]
  },
  {
    "id": "ddf8c5ea-468c-4735-9bdb-2424da14e06c",
    "title": "Selling gpu",
    "body": "The gpu is in the best condition",
    "author": "Pavel Kocev",
    "date": "16.03.2023",
    "tags": [
      "games",
      "gamess"
    ]
  },
  {
    "id": "6d252e2c-5bf7-4546-8b65-98054afae0d2",
    "title": "Selling gpu",
    "body": "The gpu is in the best condition",
    "author": "Pavel Kocev",
    "date": "16.03.2023",
    "tags": [
      "games",
      "gamess"
    ]
  },
  {
    "id": "80667fef-9612-4b18-b8c0-d180d0058407",
    "title": "Selling gpu",
    "body": "The gpu is in the best condition",
    "author": "Pavel Kocev",
    "date": "16.03.2023",
    "tags": [
      "games",
      "gamess"
    ]
  },
  {
    "id": "fca204ee-52d3-4aca-896a-c664995d80b2",
    "title": "Selling gpu",
    "body": "The gpu is in the best condition",
    "author": "Pavel Kocev",
    "date": "16.03.2023",
    "tags": [
      "games",
      "gamess"
    ]
  },
  {
    "id": "d9b6207b-eae0-48e1-a522-58889650bbb7",
    "title": "Selling gpu",
    "body": "The gpu is in the best condition",
    "author": "Pavel Kocev",
    "date": "16.03.2023",
    "tags": [
      "games",
      "gamess"
    ]
  }
]